neo4j_backup/__init__.py
neo4j_backup/_backends.py
neo4j_backup/neo4j_extractor.py
neo4j_backup/neo4j_importer.py
neo4j_backup-1.0.0.dist-info/LICENSE
neo4j_backup-1.0.0.dist-info/METADATA
neo4j_backup-1.0.0.dist-info/WHEEL
neo4j_backup-1.0.0.dist-info/top_level.txt
neo4j_backup-1.0.0.dist-info/RECORD
