Metadata-Version: 2.1
Name: neo4j_backup
Version: 1.0.0
Summary: A simple way to backup and restore Neo4j databases without using dump files.
Author-email: Andres Hyer <andreshyer@gmail.com>
Project-URL: Homepage, https://github.com/andreshyer/neo4j-backup
Keywords: neo4j
Classifier: Development Status :: 5 - Production/Stable
Classifier: License :: OSI Approved :: Apache Software License
Classifier: Programming Language :: Python :: 3
Requires-Python: >=3.6
License-File: LICENSE
Requires-Dist: neo4j >=4.3.2
Requires-Dist: tqdm >=4.10.0
